crimson/executor/__init__.py
crimson/executor/util.py
crimson_executor-0.1.0.dist-info/LICENSE
crimson_executor-0.1.0.dist-info/METADATA
crimson_executor-0.1.0.dist-info/WHEEL
crimson_executor-0.1.0.dist-info/top_level.txt
crimson_executor-0.1.0.dist-info/RECORD
